pypylon/contrib/__init__.py
pypylon/contrib/sequencer/__init__.py
pypylon/contrib/sequencer/sequencer.py
pypylon/contrib/serial_communication/__init__.py
pypylon/contrib/serial_communication/serial_communication.py
pypylon_contrib-0.1.1.dist-info/licenses/LICENSE
pypylon_contrib-0.1.1.dist-info/METADATA
pypylon_contrib-0.1.1.dist-info/WHEEL
pypylon_contrib-0.1.1.dist-info/top_level.txt
pypylon_contrib-0.1.1.dist-info/RECORD
