Metadata-Version: 2.4
Name: pypylon-contrib
Version: 0.1.1
Summary: Contrib package for the Basler pylon Camera Software Suite 'pypylon'
Author-email: Thies Moeller <thies.moeller@baslerweb.com>, Sebastian Koell <sebastian.koell@baslerweb.com>
License: Copyright (C) 2017-2021 Basler AG
Requires-Python: >=3.9
License-File: LICENSE
Requires-Dist: pypylon
Requires-Dist: numpy
Requires-Dist: opencv-python
Requires-Dist: pyserial
Provides-Extra: dev
Requires-Dist: ruff; extra == "dev"
Requires-Dist: pylint; extra == "dev"
Requires-Dist: pytest; extra == "dev"
Provides-Extra: notebook
Requires-Dist: jupyterlab; extra == "notebook"
Requires-Dist: notebook; extra == "notebook"
Requires-Dist: pandas; extra == "notebook"
Requires-Dist: matplotlib; extra == "notebook"
Requires-Dist: scikit-image; extra == "notebook"
Requires-Dist: ipywidgets; extra == "notebook"
Dynamic: license-file
